aphrodite_flash_attn_2_cuda.cpython-310-x86_64-linux-gnu.so
aphrodite_flash_attn/__init__.py
aphrodite_flash_attn/flash_attn_interface.py
aphrodite_flash_attn-2.6.1.post2.dist-info/AUTHORS
aphrodite_flash_attn-2.6.1.post2.dist-info/LICENSE
aphrodite_flash_attn-2.6.1.post2.dist-info/METADATA
aphrodite_flash_attn-2.6.1.post2.dist-info/WHEEL
aphrodite_flash_attn-2.6.1.post2.dist-info/top_level.txt
aphrodite_flash_attn-2.6.1.post2.dist-info/RECORD
